cove/__init__.py
cove/context_processors.py
cove/html_error_msg.py
cove/middleware.py
cove/settings.py
cove/tests.py
cove/urls.py
cove/views.py
cove/fixtures/bad.xlsx
cove/fixtures/badfile.json
cove/fixtures/basic.xlsx
cove/fixtures/utf8.json
cove/input/__init__.py
cove/input/models.py
cove/input/views.py
cove/input/migrations/0001_initial.py
cove/input/migrations/0002_supplieddata_current_app.py
cove/input/migrations/0003_auto_20150506_1649.py
cove/input/migrations/0004_auto_20150908_1533.py
cove/input/migrations/0005_auto_20160104_1208.py
cove/input/migrations/0006_supplieddata_rendered.py
cove/input/migrations/0007_supplied_data_schema_version.py
cove/input/migrations/0008_supplieddata_data_schema_version.py
cove/input/migrations/0009_supplieddata_parameters.py
cove/input/migrations/0010_alter_supplieddata_original_file.py
cove/input/migrations/__init__.py
cove/lib/__init__.py
cove/lib/common.py
cove/locale/en/LC_MESSAGES/django.mo
cove/locale/en/LC_MESSAGES/django.po
cove/locale/es/LC_MESSAGES/django.mo
cove/locale/es/LC_MESSAGES/django.po
cove/management/__init__.py
cove/management/commands/__init__.py
cove/management/commands/base_command.py
cove/management/commands/expire_files.py
cove/management/commands/tests.py
cove/management/commands/upload.py
cove/sass/bootstrap/_bootstrap-compass.scss
cove/sass/bootstrap/_bootstrap-mincer.scss
cove/sass/bootstrap/_bootstrap-sprockets.scss
cove/sass/bootstrap/_bootstrap.scss
cove/sass/bootstrap/bootstrap/_alerts.scss
cove/sass/bootstrap/bootstrap/_badges.scss
cove/sass/bootstrap/bootstrap/_breadcrumbs.scss
cove/sass/bootstrap/bootstrap/_button-groups.scss
cove/sass/bootstrap/bootstrap/_buttons.scss
cove/sass/bootstrap/bootstrap/_carousel.scss
cove/sass/bootstrap/bootstrap/_close.scss
cove/sass/bootstrap/bootstrap/_code.scss
cove/sass/bootstrap/bootstrap/_component-animations.scss
cove/sass/bootstrap/bootstrap/_dropdowns.scss
cove/sass/bootstrap/bootstrap/_forms.scss
cove/sass/bootstrap/bootstrap/_glyphicons.scss
libcoveweb-0.31.1.dist-info/LICENCE.rst
libcoveweb-0.31.1.dist-info/METADATA
libcoveweb-0.31.1.dist-info/WHEEL
libcoveweb-0.31.1.dist-info/top_level.txt
libcoveweb-0.31.1.dist-info/RECORD
