Metadata-Version: 2.1
Name: libcoveweb
Version: 0.31.1
Summary: UNKNOWN
Home-page: https://github.com/OpenDataServices/lib-cove-web
Author: Open Data Services
Author-email: code@opendataservices.coop
License: UNKNOWN
Platform: UNKNOWN
Classifier: License :: OSI Approved :: GNU Affero General Public License v3 or later (AGPLv3+)
Requires-Python: >=3.8
Requires-Dist: Django (<4.3,>=2.2)
Requires-Dist: django-bootstrap3
Requires-Dist: flattentool
Requires-Dist: libcove (>=0.17.0)
Requires-Dist: requests
Requires-Dist: werkzeug
Provides-Extra: test
Requires-Dist: coveralls ; extra == 'test'
Requires-Dist: flake8 ; extra == 'test'
Requires-Dist: hypothesis ; extra == 'test'
Requires-Dist: libsass ; extra == 'test'
Requires-Dist: pytest ; extra == 'test'
Requires-Dist: pytest-cov ; extra == 'test'
Requires-Dist: pytest-django ; extra == 'test'
Requires-Dist: pytest-localserver ; extra == 'test'
Requires-Dist: pytest-xdist ; extra == 'test'
Requires-Dist: selenium ; extra == 'test'
Requires-Dist: transifex-client ; extra == 'test'
